dbop_core/__init__.py
dbop_core/classify.py
dbop_core/core.py
dbop_core/otel_runtime.py
dbop_core/otel_setup.py
dbop_core/types.py
dbop_core/contrib/aiomysql_adapter.py
dbop_core/contrib/aiosqlite_adapter.py
dbop_core/contrib/asyncpg_adapter.py
dbop_core/contrib/dbapi_adapter.py
dbop_core/contrib/psycopg_adapter.py
dbop_core/contrib/sqlalchemy_adapter.py
dbop_core/contrib/sqlalchemy_adapter_async.py
dbop_core-1.1.0.dist-info/licenses/LICENSE
dbop_core-1.1.0.dist-info/METADATA
dbop_core-1.1.0.dist-info/WHEEL
dbop_core-1.1.0.dist-info/top_level.txt
dbop_core-1.1.0.dist-info/RECORD
