Metadata-Version: 2.4
Name: dbop-core
Version: 1.1.0
Summary: DB-agnostic operation runner with retries/backoff and pluggable scopes/classifiers
Author: Youssef Khaya
License: MIT
Keywords: retry,backoff,database,resilience,asyncio
Classifier: Programming Language :: Python :: 3
Classifier: Programming Language :: Python :: 3.9
Classifier: Programming Language :: Python :: 3.10
Classifier: Programming Language :: Python :: 3.11
Classifier: Programming Language :: Python :: 3.12
Classifier: Topic :: Software Development :: Libraries
Requires-Python: >=3.9
License-File: LICENSE
Provides-Extra: sqlalchemy
Requires-Dist: SQLAlchemy<3,>=2; extra == "sqlalchemy"
Provides-Extra: psycopg
Requires-Dist: psycopg[binary]>=3.1.8; extra == "psycopg"
Provides-Extra: asyncpg
Requires-Dist: asyncpg>=0.29.0; extra == "asyncpg"
Provides-Extra: aiomysql
Requires-Dist: aiomysql>=0.2.0; extra == "aiomysql"
Provides-Extra: aiosqlite
Requires-Dist: aiosqlite>=0.19.0; extra == "aiosqlite"
Provides-Extra: otel
Requires-Dist: opentelemetry-sdk>=1.25; extra == "otel"
Requires-Dist: opentelemetry-exporter-otlp>=1.25; extra == "otel"
Provides-Extra: dev
Requires-Dist: pytest<9,>=8; extra == "dev"
Requires-Dist: pytest-asyncio>=0.23; extra == "dev"
Requires-Dist: pytest-cov>=4.1; extra == "dev"
Requires-Dist: coverage>=7.4; extra == "dev"
Requires-Dist: ruff>=0.6; extra == "dev"
Requires-Dist: black>=24.3; extra == "dev"
Requires-Dist: build>=1.0; extra == "dev"
Requires-Dist: twine>=5.0; extra == "dev"
Requires-Dist: tomli>=2; python_version < "3.11" and extra == "dev"
Dynamic: license-file
